booting.py
booting-1.0.dist-info/WHEEL
booting-1.0.dist-info/METADATA
booting-1.0.dist-info/RECORD
